{"profile":{"id":"1231","name":"pueblo de javiiperez","x":547,"y":505,"k":55,"points":9528,"owner":{"id":"2145267","name":"kaidosan15","tribe":{"id":"32","tag":"LaPera"}},"firstSeen":1781216280,"lastConquest":1778583178,"conquestCount":1},"series":[{"t":1781216280,"points":9555},{"t":1781413848,"points":9571},{"t":1784000501,"points":9528}],"conquests":[{"t":1778583178,"village":{"id":"1231","name":"pueblo de javiiperez","x":547,"y":505,"points":9555},"newOwner":{"id":"2145267","name":"kaidosan15","tribe":{"id":"32","tag":"LaPera"}},"oldOwner":{"id":"2177144","name":"javiiperez","tribe":null}}]}