{"profile":{"id":"14217","name":"Pueblo de bonificación","x":592,"y":581,"k":55,"points":39,"owner":{"id":"992825","name":"las dalias","tribe":{"id":"2","tag":"ETRNLS"}},"firstSeen":1784742329,"lastConquest":1784843319,"conquestCount":1},"series":[{"t":1784742329,"points":32},{"t":1784803003,"points":38},{"t":1784829097,"points":39}],"conquests":[{"t":1784843319,"village":{"id":"14217","name":"Pueblo de bonificación","x":592,"y":581,"points":39},"newOwner":{"id":"992825","name":"las dalias","tribe":{"id":"2","tag":"ETRNLS"}},"oldOwner":null}]}