{"profile":{"id":"2445","name":"003 Noble","x":556,"y":537,"k":55,"points":9641,"owner":{"id":"2110410","name":"jeyvix","tribe":{"id":"13","tag":"WC.."}},"firstSeen":1781216280,"lastConquest":1780050703,"conquestCount":2},"series":[{"t":1781216280,"points":7937},{"t":1781821584,"points":8032},{"t":1781866726,"points":8147},{"t":1781892741,"points":8359},{"t":1781957494,"points":8496},{"t":1781966023,"points":8533},{"t":1781985506,"points":8577},{"t":1781998647,"points":8630},{"t":1782036406,"points":8725},{"t":1782044502,"points":8840},{"t":1782304196,"points":9005},{"t":1782331912,"points":9142},{"t":1782380768,"points":9307},{"t":1782405459,"points":9500},{"t":1783942409,"points":9564},{"t":1783955825,"points":9641}],"conquests":[{"t":1780050703,"village":{"id":"2445","name":"003 Noble","x":556,"y":537,"points":7937},"newOwner":{"id":"2110410","name":"jeyvix","tribe":{"id":"13","tag":"WC.."}},"oldOwner":{"id":"2179853","name":null,"tribe":null}},{"t":1778630435,"village":{"id":"2445","name":"003 Noble","x":556,"y":537,"points":7937},"newOwner":{"id":"2179853","name":null,"tribe":null},"oldOwner":null}]}