{"profile":{"id":"2515","name":"pueblo de DarkPhisley","x":481,"y":476,"k":44,"points":9860,"owner":{"id":"2180326","name":"ylaida","tribe":{"id":"98","tag":"SINTM"}},"firstSeen":1781216280,"lastConquest":1780350893,"conquestCount":1},"series":[{"t":1781216280,"points":9223},{"t":1781240746,"points":9400},{"t":1781260879,"points":9474},{"t":1781301715,"points":9562},{"t":1781343363,"points":9669},{"t":1781372841,"points":9860}],"conquests":[{"t":1780350893,"village":{"id":"2515","name":"pueblo de DarkPhisley","x":481,"y":476,"points":9223},"newOwner":{"id":"2180326","name":"ylaida","tribe":{"id":"98","tag":"SINTM"}},"oldOwner":{"id":"1985572","name":null,"tribe":null}}]}