{"profile":{"id":"2995","name":"[000]LdreaM","x":532,"y":459,"k":45,"points":8839,"owner":{"id":"933357","name":"d3byan","tribe":{"id":"32","tag":"LaPera"}},"firstSeen":1781216280,"lastConquest":null,"conquestCount":0},"series":[{"t":1781216280,"points":7387},{"t":1781734533,"points":7467},{"t":1781759076,"points":7562},{"t":1781779777,"points":7677},{"t":1782304196,"points":7792},{"t":1782390831,"points":7929},{"t":1782419019,"points":8094},{"t":1782431215,"points":8147},{"t":1782448890,"points":8211},{"t":1782491363,"points":8376},{"t":1782900983,"points":8553},{"t":1783260668,"points":8765},{"t":1783362088,"points":8839}],"conquests":[]}