{"profile":{"id":"3742","name":"[07] Cosquillas llegando","x":484,"y":443,"k":44,"points":10053,"owner":{"id":"1700496","name":"Akka","tribe":{"id":"54","tag":"SINTM"}},"firstSeen":1781216280,"lastConquest":1783228425,"conquestCount":6},"series":[{"t":1781216280,"points":5011},{"t":1781240746,"points":5121},{"t":1781326426,"points":5236},{"t":1781343363,"points":5351},{"t":1781360962,"points":5377},{"t":1781372841,"points":5408},{"t":1781380543,"points":5445},{"t":1781393645,"points":5489},{"t":1781413848,"points":5542},{"t":1781439427,"points":5679},{"t":1781459444,"points":5816},{"t":1781501398,"points":5981},{"t":1781527473,"points":6146},{"t":1781540613,"points":6226},{"t":1781562631,"points":6321},{"t":1781609810,"points":6519},{"t":1781630576,"points":6717},{"t":1781653778,"points":6832},{"t":1781695127,"points":6969},{"t":1781721366,"points":7134},{"t":1781734533,"points":7163},{"t":1781759076,"points":7242},{"t":1781798120,"points":7357},{"t":1781846839,"points":7494},{"t":1781866726,"points":7574},{"t":1781948662,"points":7739},{"t":1781991673,"points":7834},{"t":1782019199,"points":7949},{"t":1782044502,"points":8086},{"t":1782078197,"points":8251},{"t":1782131261,"points":8449},{"t":1782152337,"points":8513},{"t":1782166633,"points":8615},{"t":1782189102,"points":8692},{"t":1782813751,"points":8444},{"t":1782837182,"points":8477},{"t":1782850846,"points":8495},{"t":1782862685,"points":8522},{"t":1782881722,"points":8559},{"t":1782900983,"points":8584},{"t":1782924047,"points":8613},{"t":1782936996,"points":8649},{"t":1782966745,"points":8692},{"t":1783149390,"points":8448},{"t":1783160805,"points":8450},{"t":1783179163,"points":8465},{"t":1783186127,"points":8470},{"t":1783199684,"points":8477},{"t":1783206895,"points":8486},{"t":1783225896,"points":8522},{"t":1783243417,"points":8489},{"t":1783252113,"points":8501},{"t":1783260668,"points":8519},{"t":1783280610,"points":8531},{"t":1783286917,"points":8546},{"t":1783294149,"points":8563},{"t":1783312870,"points":8583},{"t":1783335928,"points":8608},{"t":1783353350,"points":8639},{"t":1783362088,"points":8675},{"t":1783380751,"points":8718},{"t":1783418511,"points":8772},{"t":1783427984,"points":8808},{"t":1783442548,"points":8851},{"t":1783455404,"points":8902},{"t":1783482431,"points":9025},{"t":1783583748,"points":9237},{"t":1783596008,"points":9242},{"t":1783741485,"points":9389},{"t":1783834824,"points":9566},{"t":1783942409,"points":9778},{"t":1784000501,"points":9829},{"t":1784010635,"points":9891},{"t":1784086871,"points":9965},{"t":1784116428,"points":10053}],"conquests":[{"t":1783228425,"village":{"id":"3742","name":"[07] Cosquillas llegando","x":484,"y":443,"points":8522},"newOwner":{"id":"1700496","name":"Akka","tribe":{"id":"54","tag":"SINTM"}},"oldOwner":{"id":"1424124","name":null,"tribe":null}},{"t":1783155147,"village":{"id":"3742","name":"[07] Cosquillas llegando","x":484,"y":443,"points":8450},"newOwner":{"id":"1424124","name":null,"tribe":null},"oldOwner":{"id":"2180005","name":".LeFou","tribe":{"id":"45","tag":"Pera"}}},{"t":1783155147,"village":{"id":"3742","name":"[07] Cosquillas llegando","x":484,"y":443,"points":8450},"newOwner":{"id":"1424124","name":null,"tribe":null},"oldOwner":{"id":"1424124","name":null,"tribe":null}},{"t":1783148327,"village":{"id":"3742","name":"[07] Cosquillas llegando","x":484,"y":443,"points":8448},"newOwner":{"id":"2180005","name":".LeFou","tribe":{"id":"45","tag":"Pera"}},"oldOwner":{"id":"2144474","name":"Daphnee","tribe":{"id":"80","tag":"SClass"}}},{"t":1781211703,"village":{"id":"3742","name":"[07] Cosquillas llegando","x":484,"y":443,"points":5011},"newOwner":{"id":"2144474","name":"Daphnee","tribe":{"id":"80","tag":"SClass"}},"oldOwner":{"id":"1995834","name":null,"tribe":null}},{"t":1778000410,"village":{"id":"3742","name":"[07] Cosquillas llegando","x":484,"y":443,"points":5011},"newOwner":{"id":"1995834","name":null,"tribe":null},"oldOwner":{"id":"2139680","name":null,"tribe":null}}]}