{"profile":{"id":"6385","name":"0002.","x":450,"y":433,"k":44,"points":9757,"owner":{"id":"1265225","name":"Sonny Jr.","tribe":{"id":"54","tag":"SINTM"}},"firstSeen":1781216280,"lastConquest":1778039731,"conquestCount":1},"series":[{"t":1781216280,"points":9757},{"t":1783583748,"points":9714},{"t":1783611306,"points":9757},{"t":1783657011,"points":9714},{"t":1783682430,"points":9757}],"conquests":[{"t":1778039731,"village":{"id":"6385","name":"0002.","x":450,"y":433,"points":9757},"newOwner":{"id":"1265225","name":"Sonny Jr.","tribe":{"id":"54","tag":"SINTM"}},"oldOwner":{"id":"2179727","name":null,"tribe":null}}]}