{"profile":{"id":"104","name":"Herreros Enanos Atípico","tag":"HEA 1","current":false,"rank":86,"points":0,"villages":0,"members":1,"avg":0,"od_total":1435947,"od_att":450396,"od_def":823950,"od_sup":161601,"firstSeen":1781216833,"bestRank":68,"maxPoints":600,"maxVillages":1,"conquests":0,"lost":0},"series":[{"t":1781216833,"rank":71,"points":600,"villages":1,"members":4,"od_total":1433899,"od_att":450396,"od_def":821902,"od_sup":161601},{"t":1781308451,"rank":69,"points":600,"villages":1,"members":3,"od_total":1433899,"od_att":450396,"od_def":821902,"od_sup":161601},{"t":1781393645,"rank":69,"points":600,"villages":1,"members":3,"od_total":1433899,"od_att":450396,"od_def":821902,"od_sup":161601},{"t":1781480337,"rank":68,"points":0,"villages":0,"members":3,"od_total":1435947,"od_att":450396,"od_def":823950,"od_sup":161601},{"t":1781562631,"rank":88,"points":0,"villages":0,"members":3,"od_total":1435947,"od_att":450396,"od_def":823950,"od_sup":161601},{"t":1781653778,"rank":88,"points":0,"villages":0,"members":3,"od_total":1435947,"od_att":450396,"od_def":823950,"od_sup":161601},{"t":1781740390,"rank":84,"points":0,"villages":0,"members":3,"od_total":1435947,"od_att":450396,"od_def":823950,"od_sup":161601},{"t":1781821584,"rank":84,"points":0,"villages":0,"members":2,"od_total":1435947,"od_att":450396,"od_def":823950,"od_sup":161601},{"t":1781911003,"rank":80,"points":0,"villages":0,"members":2,"od_total":1435947,"od_att":450396,"od_def":823950,"od_sup":161601},{"t":1781998647,"rank":88,"points":0,"villages":0,"members":2,"od_total":1435947,"od_att":450396,"od_def":823950,"od_sup":161601},{"t":1782085568,"rank":85,"points":0,"villages":0,"members":2,"od_total":1435947,"od_att":450396,"od_def":823950,"od_sup":161601},{"t":1782166633,"rank":86,"points":0,"villages":0,"members":2,"od_total":1435947,"od_att":450396,"od_def":823950,"od_sup":161601},{"t":1782257500,"rank":84,"points":0,"villages":0,"members":2,"od_total":1435947,"od_att":450396,"od_def":823950,"od_sup":161601},{"t":1782344129,"rank":86,"points":0,"villages":0,"members":2,"od_total":1435947,"od_att":450396,"od_def":823950,"od_sup":161601},{"t":1782431215,"rank":87,"points":0,"villages":0,"members":1,"od_total":1435947,"od_att":450396,"od_def":823950,"od_sup":161601},{"t":1782516956,"rank":89,"points":0,"villages":0,"members":1,"od_total":1435947,"od_att":450396,"od_def":823950,"od_sup":161601},{"t":1782602286,"rank":85,"points":0,"villages":0,"members":1,"od_total":1435947,"od_att":450396,"od_def":823950,"od_sup":161601},{"t":1782689481,"rank":87,"points":0,"villages":0,"members":1,"od_total":1435947,"od_att":450396,"od_def":823950,"od_sup":161601},{"t":1782775054,"rank":85,"points":0,"villages":0,"members":1,"od_total":1435947,"od_att":450396,"od_def":823950,"od_sup":161601},{"t":1782862685,"rank":86,"points":0,"villages":0,"members":1,"od_total":1435947,"od_att":450396,"od_def":823950,"od_sup":161601}],"memberList":[],"weekDays":[1783640312,1783725256,1783798405,1783897985,1783984623,1784070958,1784124962],"gains":[],"losses":[],"villages":[]}