{"profile":{"id":"1030385","name":"Dymustens","current":false,"tribe":null,"rank":991,"points":60,"villages":1,"avg":60,"od_total":557,"od_att":null,"od_def":557,"od_sup":null,"firstSeen":1781216833,"bestRank":991,"maxPoints":60,"maxVillages":1,"tribeChanges":0,"conquests":0,"lost":1},"series":[{"t":1781216833,"rank":1112,"points":60,"villages":1,"ally":"0","od_total":557,"od_att":null,"od_def":557,"od_sup":null},{"t":1781308451,"rank":1091,"points":60,"villages":1,"ally":"0","od_total":557,"od_att":null,"od_def":557,"od_sup":null},{"t":1781393645,"rank":1081,"points":60,"villages":1,"ally":"0","od_total":557,"od_att":null,"od_def":557,"od_sup":null},{"t":1781480337,"rank":1060,"points":60,"villages":1,"ally":"0","od_total":557,"od_att":null,"od_def":557,"od_sup":null},{"t":1781562631,"rank":1048,"points":60,"villages":1,"ally":"0","od_total":557,"od_att":null,"od_def":557,"od_sup":null},{"t":1781653778,"rank":1035,"points":60,"villages":1,"ally":"0","od_total":557,"od_att":null,"od_def":557,"od_sup":null},{"t":1781740390,"rank":1019,"points":60,"villages":1,"ally":"0","od_total":557,"od_att":null,"od_def":557,"od_sup":null},{"t":1781821584,"rank":1011,"points":60,"villages":1,"ally":"0","od_total":557,"od_att":null,"od_def":557,"od_sup":null},{"t":1781911003,"rank":1004,"points":60,"villages":1,"ally":"0","od_total":557,"od_att":null,"od_def":557,"od_sup":null},{"t":1781998647,"rank":996,"points":60,"villages":1,"ally":"0","od_total":557,"od_att":null,"od_def":557,"od_sup":null},{"t":1782085568,"rank":991,"points":60,"villages":1,"ally":"0","od_total":557,"od_att":null,"od_def":557,"od_sup":null}],"gains":[],"losses":[{"t":1780495043,"village":{"id":"10480","name":"02-Magnus Carlsen","x":572,"y":426,"points":2440},"newOwner":{"id":"2179769","name":"AramBuru","tribe":{"id":"32","tag":"LaPera"}},"oldOwner":{"id":"1030385","name":null,"tribe":null}}],"villages":[]}