{"profile":{"id":"1139497","name":"alloza14","current":true,"tribe":null,"rank":859,"points":0,"villages":0,"avg":0,"od_total":566404,"od_att":173169,"od_def":123620,"od_sup":269615,"firstSeen":1781216833,"bestRank":297,"maxPoints":61819,"maxVillages":11,"tribeChanges":3,"conquests":10,"lost":11},"series":[{"t":1781216833,"rank":307,"points":33740,"villages":8,"ally":"18","od_total":60676,"od_att":45658,"od_def":1457,"od_sup":13561},{"t":1781308451,"rank":305,"points":34942,"villages":8,"ally":"18","od_total":87107,"od_att":46970,"od_def":1457,"od_sup":38680},{"t":1781393645,"rank":304,"points":36255,"villages":8,"ally":"18","od_total":87313,"od_att":47028,"od_def":1457,"od_sup":38828},{"t":1781480337,"rank":297,"points":39051,"villages":8,"ally":"18","od_total":87383,"od_att":47052,"od_def":1467,"od_sup":38864},{"t":1781562631,"rank":307,"points":39636,"villages":8,"ally":"18","od_total":115687,"od_att":75299,"od_def":1467,"od_sup":38921},{"t":1781653778,"rank":309,"points":41351,"villages":9,"ally":"244","od_total":118953,"od_att":75299,"od_def":1467,"od_sup":42187},{"t":1781740390,"rank":310,"points":42785,"villages":9,"ally":"244","od_total":118953,"od_att":75299,"od_def":1467,"od_sup":42187},{"t":1781821584,"rank":309,"points":44408,"villages":9,"ally":"109","od_total":118953,"od_att":75299,"od_def":1467,"od_sup":42187},{"t":1781911003,"rank":309,"points":47116,"villages":10,"ally":"109","od_total":126225,"od_att":75366,"od_def":1467,"od_sup":49392},{"t":1781998647,"rank":305,"points":49292,"villages":10,"ally":"109","od_total":182941,"od_att":131987,"od_def":1467,"od_sup":49490},{"t":1782085568,"rank":304,"points":51406,"villages":11,"ally":"109","od_total":183697,"od_att":131987,"od_def":1535,"od_sup":50175},{"t":1782166633,"rank":303,"points":51869,"villages":11,"ally":"109","od_total":184229,"od_att":131987,"od_def":2050,"od_sup":50192},{"t":1782257500,"rank":304,"points":53687,"villages":11,"ally":"109","od_total":184533,"od_att":131987,"od_def":2326,"od_sup":81804},{"t":1782344129,"rank":300,"points":55243,"villages":11,"ally":"109","od_total":306565,"od_att":132087,"od_def":22611,"od_sup":151830},{"t":1782431215,"rank":303,"points":56438,"villages":11,"ally":"109","od_total":347674,"od_att":173078,"od_def":22715,"od_sup":151881},{"t":1782516956,"rank":298,"points":58256,"villages":11,"ally":"109","od_total":347686,"od_att":173078,"od_def":22725,"od_sup":151883},{"t":1782602286,"rank":301,"points":60632,"villages":11,"ally":"109","od_total":347686,"od_att":173078,"od_def":22725,"od_sup":151883},{"t":1782689481,"rank":307,"points":61075,"villages":11,"ally":"109","od_total":367698,"od_att":173078,"od_def":47966,"od_sup":151932},{"t":1782775054,"rank":319,"points":61163,"villages":11,"ally":"109","od_total":435686,"od_att":173078,"od_def":76059,"od_sup":186549},{"t":1782862685,"rank":315,"points":61819,"villages":11,"ally":"109","od_total":436362,"od_att":173078,"od_def":76437,"od_sup":186847},{"t":1782949538,"rank":403,"points":30100,"villages":7,"ally":"109","od_total":482434,"od_att":173078,"od_def":86553,"od_sup":222803},{"t":1783035064,"rank":417,"points":23935,"villages":6,"ally":"109","od_total":488686,"od_att":173169,"od_def":92714,"od_sup":222803},{"t":1783120783,"rank":425,"points":19957,"villages":5,"ally":"109","od_total":489124,"od_att":173169,"od_def":93147,"od_sup":222807},{"t":1783206895,"rank":678,"points":1067,"villages":1,"ally":"0","od_total":563910,"od_att":173169,"od_def":121126,"od_sup":269615},{"t":1783294149,"rank":675,"points":1067,"villages":1,"ally":"0","od_total":563942,"od_att":173169,"od_def":121158,"od_sup":269615},{"t":1783380751,"rank":966,"points":0,"villages":0,"ally":"0","od_total":566404,"od_att":173169,"od_def":123620,"od_sup":269615},{"t":1783466128,"rank":952,"points":0,"villages":0,"ally":"0","od_total":566404,"od_att":173169,"od_def":123620,"od_sup":269615},{"t":1783553467,"rank":943,"points":0,"villages":0,"ally":"0","od_total":566404,"od_att":173169,"od_def":123620,"od_sup":269615},{"t":1783640312,"rank":954,"points":0,"villages":0,"ally":"0","od_total":566404,"od_att":173169,"od_def":123620,"od_sup":269615},{"t":1783725256,"rank":943,"points":0,"villages":0,"ally":"0","od_total":566404,"od_att":173169,"od_def":123620,"od_sup":269615},{"t":1783798405,"rank":934,"points":0,"villages":0,"ally":"0","od_total":566404,"od_att":173169,"od_def":123620,"od_sup":269615},{"t":1783897985,"rank":927,"points":0,"villages":0,"ally":"0","od_total":566404,"od_att":173169,"od_def":123620,"od_sup":269615},{"t":1783984623,"rank":915,"points":0,"villages":0,"ally":"0","od_total":566404,"od_att":173169,"od_def":123620,"od_sup":269615},{"t":1784070958,"rank":903,"points":0,"villages":0,"ally":"0","od_total":566404,"od_att":173169,"od_def":123620,"od_sup":269615},{"t":1784157914,"rank":891,"points":0,"villages":0,"ally":"0","od_total":566404,"od_att":173169,"od_def":123620,"od_sup":269615},{"t":1784243697,"rank":875,"points":0,"villages":0,"ally":"0","od_total":566404,"od_att":173169,"od_def":123620,"od_sup":269615},{"t":1784329909,"rank":872,"points":0,"villages":0,"ally":"0","od_total":566404,"od_att":173169,"od_def":123620,"od_sup":269615},{"t":1784416465,"rank":859,"points":0,"villages":0,"ally":"0","od_total":566404,"od_att":173169,"od_def":123620,"od_sup":269615}],"gains":[{"t":1782082344,"village":{"id":"6343","name":"014 Buddhas Family","x":445,"y":571,"points":1180},"newOwner":{"id":"1139497","name":"alloza14","tribe":null},"oldOwner":{"id":"2179984","name":null,"tribe":null}},{"t":1781844691,"village":{"id":"12261","name":"[F] 059 - Genes -","x":436,"y":596,"points":221},"newOwner":{"id":"1139497","name":"alloza14","tribe":null},"oldOwner":null},{"t":1781607506,"village":{"id":"13209","name":"074 Alvaro Riquelme","x":441,"y":605,"points":30},"newOwner":{"id":"1139497","name":"alloza14","tribe":null},"oldOwner":null},{"t":1781137194,"village":{"id":"10239","name":"SO021","x":450,"y":589,"points":549},"newOwner":{"id":"1139497","name":"alloza14","tribe":null},"oldOwner":null},{"t":1780634325,"village":{"id":"11311","name":"072 Alvaro Riquelme","x":442,"y":593,"points":2736},"newOwner":{"id":"1139497","name":"alloza14","tribe":null},"oldOwner":{"id":"875478","name":"nznznz","tribe":null}},{"t":1780507079,"village":{"id":"10771","name":"044 OverCurry","x":447,"y":590,"points":2509},"newOwner":{"id":"1139497","name":"alloza14","tribe":null},"oldOwner":{"id":"2179275","name":null,"tribe":null}},{"t":1780415149,"village":{"id":"12240","name":"[F] 055 - alloza14 -","x":437,"y":592,"points":1540},"newOwner":{"id":"1139497","name":"alloza14","tribe":null},"oldOwner":null},{"t":1780171803,"village":{"id":"11041","name":"045 OverCurry","x":447,"y":591,"points":2603},"newOwner":{"id":"1139497","name":"alloza14","tribe":null},"oldOwner":null},{"t":1779540362,"village":{"id":"9729","name":"039 Less «","x":449,"y":588,"points":5406},"newOwner":{"id":"1139497","name":"alloza14","tribe":null},"oldOwner":null},{"t":1779416241,"village":{"id":"997","name":"B002 Noble","x":442,"y":569,"points":8271},"newOwner":{"id":"1139497","name":"alloza14","tribe":null},"oldOwner":{"id":"2081910","name":null,"tribe":null}}],"losses":[{"t":1783329535,"village":{"id":"12261","name":"[F] 059 - Genes -","x":436,"y":596,"points":1058},"newOwner":{"id":"1169034","name":"Vanquished","tribe":{"id":"13","tag":"WC.."}},"oldOwner":{"id":"1139497","name":"alloza14","tribe":null}},{"t":1783201896,"village":{"id":"6343","name":"014 Buddhas Family","x":445,"y":571,"points":2434},"newOwner":{"id":"1617877","name":"Baalcells98","tribe":{"id":"13","tag":"WC.."}},"oldOwner":{"id":"1139497","name":"alloza14","tribe":null}},{"t":1783174262,"village":{"id":"13209","name":"074 Alvaro Riquelme","x":441,"y":605,"points":839},"newOwner":{"id":"1833730","name":"tony montanaa","tribe":{"id":"13","tag":"WC.."}},"oldOwner":{"id":"1139497","name":"alloza14","tribe":null}},{"t":1783162418,"village":{"id":"997","name":"B002 Noble","x":442,"y":569,"points":9546},"newOwner":{"id":"1896176","name":"Zopp.","tribe":{"id":"27","tag":"WC"}},"oldOwner":{"id":"1139497","name":"alloza14","tribe":null}},{"t":1783158025,"village":{"id":"12240","name":"[F] 055 - alloza14 -","x":437,"y":592,"points":5119},"newOwner":{"id":"1169034","name":"Vanquished","tribe":{"id":"13","tag":"WC.."}},"oldOwner":{"id":"1139497","name":"alloza14","tribe":null}},{"t":1783054975,"village":{"id":"10239","name":"SO021","x":450,"y":589,"points":4259},"newOwner":{"id":"2098940","name":"paparrot","tribe":{"id":"13","tag":"WC.."}},"oldOwner":{"id":"1139497","name":"alloza14","tribe":null}},{"t":1783005961,"village":{"id":"11311","name":"072 Alvaro Riquelme","x":442,"y":593,"points":6418},"newOwner":{"id":"1833730","name":"tony montanaa","tribe":{"id":"13","tag":"WC.."}},"oldOwner":{"id":"1139497","name":"alloza14","tribe":null}},{"t":1782936558,"village":{"id":"9253","name":"040 Less «","x":449,"y":586,"points":9302},"newOwner":{"id":"2122269","name":"lenttt","tribe":{"id":"13","tag":"WC.."}},"oldOwner":{"id":"1139497","name":"alloza14","tribe":null}},{"t":1782925810,"village":{"id":"10771","name":"044 OverCurry","x":447,"y":590,"points":7328},"newOwner":{"id":"1911553","name":"Overground","tribe":{"id":"13","tag":"WC.."}},"oldOwner":{"id":"1139497","name":"alloza14","tribe":null}},{"t":1782921950,"village":{"id":"11041","name":"045 OverCurry","x":447,"y":591,"points":5580},"newOwner":{"id":"1911553","name":"Overground","tribe":{"id":"13","tag":"WC.."}},"oldOwner":{"id":"1139497","name":"alloza14","tribe":null}},{"t":1782893767,"village":{"id":"9729","name":"039 Less «","x":449,"y":588,"points":9804},"newOwner":{"id":"2122269","name":"lenttt","tribe":{"id":"13","tag":"WC.."}},"oldOwner":{"id":"1139497","name":"alloza14","tribe":null}}],"villages":[]}