{"profile":{"id":"1888291","name":"granjeo","current":true,"tribe":{"id":"13","tag":"WC.."},"rank":78,"points":340561,"villages":43,"avg":7920,"od_total":2009013,"od_att":1258161,"od_def":614586,"od_sup":136266,"firstSeen":1781216833,"bestRank":63,"maxPoints":340561,"maxVillages":43,"tribeChanges":0,"conquests":46,"lost":4},"series":[{"t":1781216833,"rank":90,"points":84375,"villages":15,"ally":"13","od_total":142315,"od_att":119482,"od_def":5705,"od_sup":17128},{"t":1781308451,"rank":93,"points":86494,"villages":15,"ally":"13","od_total":142373,"od_att":119532,"od_def":5713,"od_sup":17128},{"t":1781393645,"rank":94,"points":90591,"villages":16,"ally":"13","od_total":143903,"od_att":119619,"od_def":7156,"od_sup":17128},{"t":1781480337,"rank":93,"points":95701,"villages":19,"ally":"13","od_total":165135,"od_att":119642,"od_def":13281,"od_sup":32212},{"t":1781562631,"rank":93,"points":98621,"villages":19,"ally":"13","od_total":165274,"od_att":119770,"od_def":13281,"od_sup":32223},{"t":1781653778,"rank":94,"points":102854,"villages":20,"ally":"13","od_total":165490,"od_att":119770,"od_def":13494,"od_sup":32226},{"t":1781740390,"rank":96,"points":106608,"villages":20,"ally":"13","od_total":165690,"od_att":119770,"od_def":13694,"od_sup":32226},{"t":1781821584,"rank":96,"points":110761,"villages":20,"ally":"13","od_total":165723,"od_att":119770,"od_def":13726,"od_sup":32227},{"t":1781911003,"rank":94,"points":114524,"villages":20,"ally":"13","od_total":226399,"od_att":180405,"od_def":13760,"od_sup":32234},{"t":1781998647,"rank":87,"points":125050,"villages":21,"ally":"13","od_total":226807,"od_att":180682,"od_def":13892,"od_sup":32242},{"t":1782085568,"rank":80,"points":138576,"villages":23,"ally":"13","od_total":233154,"od_att":186289,"od_def":14607,"od_sup":32258},{"t":1782166633,"rank":81,"points":142237,"villages":23,"ally":"13","od_total":311479,"od_att":210031,"od_def":69082,"od_sup":32366},{"t":1782257500,"rank":83,"points":146992,"villages":23,"ally":"13","od_total":313530,"od_att":240530,"od_def":69205,"od_sup":32372},{"t":1782344129,"rank":83,"points":153329,"villages":23,"ally":"13","od_total":581216,"od_att":301583,"od_def":247259,"od_sup":32373},{"t":1782431215,"rank":83,"points":158333,"villages":23,"ally":"13","od_total":623902,"od_att":344268,"od_def":247259,"od_sup":32375},{"t":1782516956,"rank":73,"points":178226,"villages":25,"ally":"13","od_total":779454,"od_att":499799,"od_def":247299,"od_sup":32376},{"t":1782602286,"rank":66,"points":191258,"villages":26,"ally":"13","od_total":783303,"od_att":503274,"od_def":247653,"od_sup":32376},{"t":1782689481,"rank":67,"points":196638,"villages":26,"ally":"13","od_total":833909,"od_att":542239,"od_def":247713,"od_sup":48786},{"t":1782775054,"rank":67,"points":202388,"villages":28,"ally":"13","od_total":972355,"od_att":673745,"od_def":248306,"od_sup":50304},{"t":1782862685,"rank":65,"points":214630,"villages":29,"ally":"13","od_total":1175850,"od_att":712220,"od_def":413326,"od_sup":50304},{"t":1782949538,"rank":68,"points":218019,"villages":29,"ally":"13","od_total":1402221,"od_att":745978,"od_def":604416,"od_sup":51827},{"t":1783035064,"rank":68,"points":226079,"villages":30,"ally":"13","od_total":1403717,"od_att":746843,"od_def":605004,"od_sup":51870},{"t":1783120783,"rank":71,"points":228075,"villages":30,"ally":"13","od_total":1403940,"od_att":746843,"od_def":605214,"od_sup":51881},{"t":1783206895,"rank":68,"points":242549,"villages":32,"ally":"13","od_total":1420670,"od_att":761237,"od_def":605328,"od_sup":54105},{"t":1783294149,"rank":69,"points":247056,"villages":32,"ally":"13","od_total":1427781,"od_att":768262,"od_def":605410,"od_sup":54109},{"t":1783380751,"rank":71,"points":253220,"villages":33,"ally":"13","od_total":1453405,"od_att":793709,"od_def":605556,"od_sup":54140},{"t":1783466128,"rank":67,"points":270882,"villages":35,"ally":"13","od_total":1470344,"od_att":810319,"od_def":605595,"od_sup":54420},{"t":1783553467,"rank":63,"points":294651,"villages":38,"ally":"13","od_total":1506928,"od_att":846315,"od_def":605801,"od_sup":54812},{"t":1783640312,"rank":63,"points":300022,"villages":38,"ally":"13","od_total":1541149,"od_att":879845,"od_def":606435,"od_sup":54869},{"t":1783725256,"rank":63,"points":304049,"villages":38,"ally":"13","od_total":1541238,"od_att":879845,"od_def":606435,"od_sup":54958},{"t":1783798405,"rank":65,"points":306506,"villages":38,"ally":"13","od_total":1541334,"od_att":879855,"od_def":606435,"od_sup":55044},{"t":1783897985,"rank":70,"points":310033,"villages":38,"ally":"13","od_total":1545260,"od_att":879855,"od_def":606471,"od_sup":58916},{"t":1783984623,"rank":70,"points":313836,"villages":38,"ally":"13","od_total":1557507,"od_att":879855,"od_def":613611,"od_sup":64089},{"t":1784070958,"rank":70,"points":319013,"villages":39,"ally":"13","od_total":1899697,"od_att":1218124,"od_def":614150,"od_sup":67423},{"t":1784157914,"rank":69,"points":325717,"villages":42,"ally":"13","od_total":1984334,"od_att":1244100,"od_def":614440,"od_sup":125794},{"t":1784243697,"rank":71,"points":329461,"villages":42,"ally":"13","od_total":1996079,"od_att":1252249,"od_def":614566,"od_sup":129264},{"t":1784329909,"rank":72,"points":333712,"villages":43,"ally":"13","od_total":2005501,"od_att":1258033,"od_def":614586,"od_sup":132882},{"t":1784416465,"rank":75,"points":338003,"villages":43,"ally":"13","od_total":2007398,"od_att":1258161,"od_def":614586,"od_sup":134651},{"t":1784460862,"rank":78,"points":340561,"villages":43,"ally":"13","od_total":2009013,"od_att":1258161,"od_def":614586,"od_sup":136266}],"gains":[{"t":1784258386,"village":{"id":"12516","name":"Z02- craft","x":608,"y":543,"points":499},"newOwner":{"id":"1888291","name":"granjeo","tribe":{"id":"13","tag":"WC.."}},"oldOwner":null},{"t":1784153547,"village":{"id":"6043","name":"040- bicjo","x":552,"y":550,"points":919},"newOwner":{"id":"1888291","name":"granjeo","tribe":{"id":"13","tag":"WC.."}},"oldOwner":null},{"t":1784125607,"village":{"id":"12276","name":"Z01-avanc","x":607,"y":544,"points":524},"newOwner":{"id":"1888291","name":"granjeo","tribe":{"id":"13","tag":"WC.."}},"oldOwner":null},{"t":1784122984,"village":{"id":"10965","name":"039- aerv","x":573,"y":576,"points":617},"newOwner":{"id":"1888291","name":"granjeo","tribe":{"id":"13","tag":"WC.."}},"oldOwner":null},{"t":1784023600,"village":{"id":"432","name":"016- Jerjes","x":484,"y":530,"points":7904},"newOwner":{"id":"1888291","name":"granjeo","tribe":{"id":"13","tag":"WC.."}},"oldOwner":{"id":"10553","name":"wtfmate","tribe":null}},{"t":1784000620,"village":{"id":"1658","name":"038- hormi","x":469,"y":530,"points":1485},"newOwner":{"id":"1888291","name":"granjeo","tribe":{"id":"13","tag":"WC.."}},"oldOwner":null},{"t":1783544935,"village":{"id":"8207","name":"033- bit","x":487,"y":594,"points":1538},"newOwner":{"id":"1888291","name":"granjeo","tribe":{"id":"13","tag":"WC.."}},"oldOwner":null},{"t":1783514662,"village":{"id":"1579","name":"031- cojin","x":506,"y":525,"points":5893},"newOwner":{"id":"1888291","name":"granjeo","tribe":{"id":"13","tag":"WC.."}},"oldOwner":{"id":"1695345","name":"elsudri","tribe":{"id":"27","tag":"WC"}}},{"t":1783488420,"village":{"id":"679","name":"032- print","x":503,"y":523,"points":9582},"newOwner":{"id":"1888291","name":"granjeo","tribe":{"id":"13","tag":"WC.."}},"oldOwner":{"id":"1695345","name":"elsudri","tribe":{"id":"27","tag":"WC"}}},{"t":1783419151,"village":{"id":"2728","name":"034-Abd","x":435,"y":563,"points":5010},"newOwner":{"id":"1888291","name":"granjeo","tribe":{"id":"13","tag":"WC.."}},"oldOwner":{"id":"2075467","name":"Tu Amo y Señor","tribe":null}},{"t":1783410526,"village":{"id":"5391","name":"037- hormiga","x":533,"y":564,"points":9067},"newOwner":{"id":"1888291","name":"granjeo","tribe":{"id":"13","tag":"WC.."}},"oldOwner":{"id":"30277","name":null,"tribe":null}},{"t":1783368387,"village":{"id":"8330","name":"030- penalty","x":484,"y":594,"points":1120},"newOwner":{"id":"1888291","name":"granjeo","tribe":{"id":"13","tag":"WC.."}},"oldOwner":null},{"t":1783324943,"village":{"id":"3306","name":".GeN.","x":468,"y":514,"points":6116},"newOwner":{"id":"1888291","name":"granjeo","tribe":{"id":"13","tag":"WC.."}},"oldOwner":{"id":"2177352","name":"emmeny","tribe":{"id":"135","tag":"SicLic"}}},{"t":1783159561,"village":{"id":"5674","name":"027- loy","x":439,"y":570,"points":7449},"newOwner":{"id":"1888291","name":"granjeo","tribe":{"id":"13","tag":"WC.."}},"oldOwner":{"id":"2178925","name":null,"tribe":null}},{"t":1783159330,"village":{"id":"11533","name":"028-abu","x":437,"y":593,"points":3266},"newOwner":{"id":"1888291","name":"granjeo","tribe":{"id":"13","tag":"WC.."}},"oldOwner":{"id":"2178680","name":"DrKGuii","tribe":null}},{"t":1783011867,"village":{"id":"11389","name":"029- berr","x":448,"y":599,"points":4762},"newOwner":{"id":"1888291","name":"granjeo","tribe":{"id":"13","tag":"WC.."}},"oldOwner":{"id":"1939848","name":"DaenerysThargarien","tribe":{"id":"18","tag":"DREAM"}}},{"t":1782830340,"village":{"id":"1497","name":"000027-neighbor","x":470,"y":512,"points":8639},"newOwner":{"id":"1888291","name":"granjeo","tribe":{"id":"13","tag":"WC.."}},"oldOwner":{"id":"1982595","name":"Harloy","tribe":{"id":"8","tag":"FILA"}}},{"t":1782830340,"village":{"id":"1497","name":"000027-neighbor","x":470,"y":512,"points":8639},"newOwner":{"id":"1888291","name":"granjeo","tribe":{"id":"13","tag":"WC.."}},"oldOwner":{"id":"1888291","name":"granjeo","tribe":{"id":"13","tag":"WC.."}}},{"t":1782767706,"village":{"id":"9722","name":"026 - estatua","x":565,"y":579,"points":612},"newOwner":{"id":"1888291","name":"granjeo","tribe":{"id":"13","tag":"WC.."}},"oldOwner":null},{"t":1782700821,"village":{"id":"10977","name":"025- foto","x":572,"y":581,"points":387},"newOwner":{"id":"1888291","name":"granjeo","tribe":{"id":"13","tag":"WC.."}},"oldOwner":null},{"t":1782598017,"village":{"id":"3696","name":"035-kadabra","x":507,"y":537,"points":9056},"newOwner":{"id":"1888291","name":"granjeo","tribe":{"id":"13","tag":"WC.."}},"oldOwner":{"id":"2123065","name":"ElMagoBK","tribe":{"id":"215","tag":"WC."}}},{"t":1782502092,"village":{"id":"754","name":"036- magic","x":505,"y":538,"points":9738},"newOwner":{"id":"1888291","name":"granjeo","tribe":{"id":"13","tag":"WC.."}},"oldOwner":{"id":"2123065","name":"ElMagoBK","tribe":{"id":"215","tag":"WC."}}},{"t":1782472980,"village":{"id":"10173","name":"024- hierro","x":467,"y":599,"points":6409},"newOwner":{"id":"1888291","name":"granjeo","tribe":{"id":"13","tag":"WC.."}},"oldOwner":{"id":"2180102","name":null,"tribe":null}},{"t":1782078611,"village":{"id":"7609","name":"023-wara","x":484,"y":591,"points":8668},"newOwner":{"id":"1888291","name":"granjeo","tribe":{"id":"13","tag":"WC.."}},"oldOwner":{"id":"1592779","name":"Persiquitore","tribe":null}},{"t":1782071399,"village":{"id":"9597","name":"022- curry","x":569,"y":577,"points":465},"newOwner":{"id":"1888291","name":"granjeo","tribe":{"id":"13","tag":"WC.."}},"oldOwner":null},{"t":1781919558,"village":{"id":"7246","name":"021- barco","x":490,"y":584,"points":6949},"newOwner":{"id":"1888291","name":"granjeo","tribe":{"id":"13","tag":"WC.."}},"oldOwner":{"id":"1592779","name":"Persiquitore","tribe":null}},{"t":1781571355,"village":{"id":"9873","name":"020- lejanía","x":501,"y":604,"points":415},"newOwner":{"id":"1888291","name":"granjeo","tribe":{"id":"13","tag":"WC.."}},"oldOwner":null},{"t":1781442430,"village":{"id":"5890","name":"019- toston","x":485,"y":531,"points":337},"newOwner":{"id":"1888291","name":"granjeo","tribe":{"id":"13","tag":"WC.."}},"oldOwner":null},{"t":1781440741,"village":{"id":"4112","name":"018- cartucho","x":488,"y":533,"points":545},"newOwner":{"id":"1888291","name":"granjeo","tribe":{"id":"13","tag":"WC.."}},"oldOwner":null},{"t":1781437728,"village":{"id":"3101","name":"017- lamparilla","x":488,"y":532,"points":513},"newOwner":{"id":"1888291","name":"granjeo","tribe":{"id":"13","tag":"WC.."}},"oldOwner":null},{"t":1781380408,"village":{"id":"432","name":"016- Jerjes","x":484,"y":530,"points":675},"newOwner":{"id":"1888291","name":"granjeo","tribe":{"id":"13","tag":"WC.."}},"oldOwner":null},{"t":1781135219,"village":{"id":"7095","name":"015- The End","x":540,"y":576,"points":2823},"newOwner":{"id":"1888291","name":"granjeo","tribe":{"id":"13","tag":"WC.."}},"oldOwner":{"id":"748151","name":"hectorleo","tribe":{"id":"22","tag":"CON."}}},{"t":1781135219,"village":{"id":"7095","name":"015- The End","x":540,"y":576,"points":2823},"newOwner":{"id":"1888291","name":"granjeo","tribe":{"id":"13","tag":"WC.."}},"oldOwner":{"id":"1888291","name":"granjeo","tribe":{"id":"13","tag":"WC.."}}},{"t":1781055260,"village":{"id":"7884","name":"014- tira","x":549,"y":576,"points":7490},"newOwner":{"id":"1888291","name":"granjeo","tribe":{"id":"13","tag":"WC.."}},"oldOwner":{"id":"2180041","name":null,"tribe":null}},{"t":1780958021,"village":{"id":"484","name":"013- y si no","x":510,"y":584,"points":4848},"newOwner":{"id":"1888291","name":"granjeo","tribe":{"id":"13","tag":"WC.."}},"oldOwner":{"id":"1643348","name":null,"tribe":null}},{"t":1780795225,"village":{"id":"9585","name":"011- caja","x":566,"y":578,"points":5678},"newOwner":{"id":"1888291","name":"granjeo","tribe":{"id":"13","tag":"WC.."}},"oldOwner":{"id":"2175064","name":"BioreNaKlate","tribe":{"id":"226","tag":"50MP"}}},{"t":1780794510,"village":{"id":"9352","name":"012-perro verde","x":563,"y":581,"points":5022},"newOwner":{"id":"1888291","name":"granjeo","tribe":{"id":"13","tag":"WC.."}},"oldOwner":{"id":"2175064","name":"BioreNaKlate","tribe":{"id":"226","tag":"50MP"}}},{"t":1780569085,"village":{"id":"6807","name":"010- boli","x":541,"y":570,"points":2148},"newOwner":{"id":"1888291","name":"granjeo","tribe":{"id":"13","tag":"WC.."}},"oldOwner":null},{"t":1780271024,"village":{"id":"2976","name":"009-fake","x":531,"y":566,"points":8085},"newOwner":{"id":"1888291","name":"granjeo","tribe":{"id":"13","tag":"WC.."}},"oldOwner":{"id":"2179565","name":null,"tribe":null}},{"t":1780169346,"village":{"id":"486","name":"008- quick","x":532,"y":557,"points":2598},"newOwner":{"id":"1888291","name":"granjeo","tribe":{"id":"13","tag":"WC.."}},"oldOwner":null},{"t":1780007962,"village":{"id":"4224","name":"007-Muk","x":550,"y":552,"points":7946},"newOwner":{"id":"1888291","name":"granjeo","tribe":{"id":"13","tag":"WC.."}},"oldOwner":{"id":"2179844","name":null,"tribe":null}},{"t":1779666616,"village":{"id":"8668","name":"006-lepanto","x":535,"y":564,"points":7768},"newOwner":{"id":"1888291","name":"granjeo","tribe":{"id":"13","tag":"WC.."}},"oldOwner":{"id":"2180190","name":null,"tribe":null}},{"t":1779062460,"village":{"id":"4309","name":"005- cart","x":488,"y":534,"points":6112},"newOwner":{"id":"1888291","name":"granjeo","tribe":{"id":"13","tag":"WC.."}},"oldOwner":{"id":"1617970","name":null,"tribe":null}},{"t":1778854047,"village":{"id":"3735","name":"004-panderia","x":495,"y":526,"points":4038},"newOwner":{"id":"1888291","name":"granjeo","tribe":{"id":"13","tag":"WC.."}},"oldOwner":null},{"t":1778460114,"village":{"id":"7975","name":"002-Griterío","x":498,"y":528,"points":7231},"newOwner":{"id":"1888291","name":"granjeo","tribe":{"id":"13","tag":"WC.."}},"oldOwner":{"id":"2180074","name":null,"tribe":null}},{"t":1778407937,"village":{"id":"9400","name":"003-Gugnir","x":505,"y":533,"points":6622},"newOwner":{"id":"1888291","name":"granjeo","tribe":{"id":"13","tag":"WC.."}},"oldOwner":{"id":"2179501","name":null,"tribe":null}}],"losses":[{"t":1784000725,"village":{"id":"432","name":"016- Jerjes","x":484,"y":530,"points":8410},"newOwner":{"id":"10553","name":"wtfmate","tribe":null},"oldOwner":{"id":"1888291","name":"granjeo","tribe":{"id":"13","tag":"WC.."}}},{"t":1783329100,"village":{"id":"3306","name":".GeN.","x":468,"y":514,"points":6116},"newOwner":{"id":"1982595","name":"Harloy","tribe":{"id":"8","tag":"FILA"}},"oldOwner":{"id":"1888291","name":"granjeo","tribe":{"id":"13","tag":"WC.."}}},{"t":1782830340,"village":{"id":"1497","name":"000027-neighbor","x":470,"y":512,"points":8639},"newOwner":{"id":"1888291","name":"granjeo","tribe":{"id":"13","tag":"WC.."}},"oldOwner":{"id":"1888291","name":"granjeo","tribe":{"id":"13","tag":"WC.."}}},{"t":1781135219,"village":{"id":"7095","name":"015- The End","x":540,"y":576,"points":2823},"newOwner":{"id":"1888291","name":"granjeo","tribe":{"id":"13","tag":"WC.."}},"oldOwner":{"id":"1888291","name":"granjeo","tribe":{"id":"13","tag":"WC.."}}}],"villages":[{"id":"1497","name":"000027-neighbor","x":470,"y":512,"k":54,"points":9825},{"id":"1399","name":"001-Gleipnir","x":504,"y":526,"k":55,"points":9269},{"id":"7975","name":"002-Griterío","x":498,"y":528,"k":54,"points":9495},{"id":"9400","name":"003-Gugnir","x":505,"y":533,"k":55,"points":9624},{"id":"3735","name":"004-panderia","x":495,"y":526,"k":54,"points":8170},{"id":"4309","name":"005- cart","x":488,"y":534,"k":54,"points":9976},{"id":"8668","name":"006-lepanto","x":535,"y":564,"k":55,"points":9465},{"id":"4224","name":"007-Muk","x":550,"y":552,"k":55,"points":9880},{"id":"486","name":"008- quick","x":532,"y":557,"k":55,"points":8190},{"id":"2976","name":"009-fake","x":531,"y":566,"k":55,"points":10076},{"id":"6807","name":"010- boli","x":541,"y":570,"k":55,"points":9603},{"id":"9585","name":"011- caja","x":566,"y":578,"k":55,"points":9718},{"id":"9352","name":"012-perro verde","x":563,"y":581,"k":55,"points":9619},{"id":"484","name":"013- y si no","x":510,"y":584,"k":55,"points":9614},{"id":"7884","name":"014- tira","x":549,"y":576,"k":55,"points":9838},{"id":"7095","name":"015- The End","x":540,"y":576,"k":55,"points":9603},{"id":"432","name":"016- Jerjes","x":484,"y":530,"k":54,"points":9464},{"id":"3101","name":"017- lamparilla","x":488,"y":532,"k":54,"points":8920},{"id":"4112","name":"018- cartucho","x":488,"y":533,"k":54,"points":7755},{"id":"5890","name":"019- toston","x":485,"y":531,"k":54,"points":8920},{"id":"9873","name":"020- lejanía","x":501,"y":604,"k":65,"points":8599},{"id":"7246","name":"021- barco","x":490,"y":584,"k":54,"points":9496},{"id":"9597","name":"022- curry","x":569,"y":577,"k":55,"points":8648},{"id":"7609","name":"023-wara","x":484,"y":591,"k":54,"points":9803},{"id":"10173","name":"024- hierro","x":467,"y":599,"k":54,"points":9027},{"id":"10977","name":"025- foto","x":572,"y":581,"k":55,"points":4848},{"id":"9722","name":"026 - estatua","x":565,"y":579,"k":55,"points":5671},{"id":"5674","name":"027- loy","x":439,"y":570,"k":54,"points":8569},{"id":"11533","name":"028-abu","x":437,"y":593,"k":54,"points":7669},{"id":"11389","name":"029- berr","x":448,"y":599,"k":54,"points":10074},{"id":"8330","name":"030- penalty","x":484,"y":594,"k":54,"points":3757},{"id":"1579","name":"031- cojin","x":506,"y":525,"k":55,"points":7326},{"id":"679","name":"032- print","x":503,"y":523,"k":55,"points":9914},{"id":"8207","name":"033- bit","x":487,"y":594,"k":54,"points":5109},{"id":"2728","name":"034-Abd","x":435,"y":563,"k":54,"points":7630},{"id":"3696","name":"035-kadabra","x":507,"y":537,"k":55,"points":9907},{"id":"754","name":"036- magic","x":505,"y":538,"k":55,"points":9879},{"id":"5391","name":"037- hormiga","x":533,"y":564,"k":55,"points":9615},{"id":"1658","name":"038- hormi","x":469,"y":530,"k":54,"points":2744},{"id":"10965","name":"039- aerv","x":573,"y":576,"k":55,"points":1146},{"id":"6043","name":"040- bicjo","x":552,"y":550,"k":55,"points":1739},{"id":"12276","name":"Z01-avanc","x":607,"y":544,"k":56,"points":1657},{"id":"12516","name":"Z02- craft","x":608,"y":543,"k":56,"points":710}]}