{"profile":{"id":"2010115","name":"canmu","current":true,"tribe":null,"rank":761,"points":26,"villages":1,"avg":26,"od_total":333451,"od_att":129489,"od_def":143137,"od_sup":60825,"firstSeen":1781216833,"bestRank":284,"maxPoints":77151,"maxVillages":11,"tribeChanges":1,"conquests":18,"lost":20},"series":[{"t":1781216833,"rank":588,"points":4840,"villages":1,"ally":"54","od_total":41709,"od_att":33687,"od_def":1693,"od_sup":6329},{"t":1781308451,"rank":592,"points":4840,"villages":1,"ally":"54","od_total":41709,"od_att":33687,"od_def":1693,"od_sup":6329},{"t":1781393645,"rank":561,"points":6127,"villages":2,"ally":"54","od_total":41748,"od_att":33687,"od_def":1732,"od_sup":6329},{"t":1781480337,"rank":557,"points":6644,"villages":2,"ally":"54","od_total":41748,"od_att":33687,"od_def":1732,"od_sup":6329},{"t":1781562631,"rank":539,"points":7965,"villages":3,"ally":"54","od_total":41761,"od_att":33687,"od_def":1740,"od_sup":6334},{"t":1781653778,"rank":523,"points":8787,"villages":3,"ally":"54","od_total":41985,"od_att":33687,"od_def":1964,"od_sup":6334},{"t":1781740390,"rank":511,"points":9242,"villages":3,"ally":"54","od_total":42002,"od_att":33687,"od_def":1974,"od_sup":6341},{"t":1781821584,"rank":497,"points":10819,"villages":4,"ally":"54","od_total":42039,"od_att":33687,"od_def":2010,"od_sup":6342},{"t":1781911003,"rank":492,"points":11679,"villages":4,"ally":"54","od_total":42039,"od_att":33687,"od_def":2010,"od_sup":6342},{"t":1781998647,"rank":488,"points":12447,"villages":4,"ally":"54","od_total":42402,"od_att":33854,"od_def":2206,"od_sup":6342},{"t":1782085568,"rank":483,"points":12939,"villages":4,"ally":"54","od_total":42459,"od_att":33874,"od_def":2242,"od_sup":6343},{"t":1782166633,"rank":478,"points":12939,"villages":4,"ally":"54","od_total":42459,"od_att":33874,"od_def":2242,"od_sup":6343},{"t":1782257500,"rank":469,"points":14549,"villages":5,"ally":"54","od_total":43165,"od_att":33874,"od_def":2948,"od_sup":6343},{"t":1782344129,"rank":461,"points":15643,"villages":5,"ally":"54","od_total":43208,"od_att":33874,"od_def":2974,"od_sup":6344},{"t":1782431215,"rank":447,"points":17751,"villages":6,"ally":"54","od_total":43421,"od_att":33874,"od_def":3202,"od_sup":6345},{"t":1782516956,"rank":435,"points":19929,"villages":7,"ally":"54","od_total":43492,"od_att":33929,"od_def":3212,"od_sup":6351},{"t":1782602286,"rank":428,"points":21713,"villages":7,"ally":"54","od_total":43513,"od_att":33929,"od_def":3232,"od_sup":6352},{"t":1782689481,"rank":429,"points":22740,"villages":7,"ally":"54","od_total":43539,"od_att":33929,"od_def":3268,"od_sup":6352},{"t":1782775054,"rank":420,"points":24929,"villages":7,"ally":"54","od_total":43569,"od_att":33929,"od_def":3288,"od_sup":6352},{"t":1782862685,"rank":416,"points":26386,"villages":7,"ally":"54","od_total":44247,"od_att":34499,"od_def":3396,"od_sup":6352},{"t":1782949538,"rank":376,"points":38036,"villages":8,"ally":"54","od_total":48599,"od_att":38844,"od_def":3402,"od_sup":6353},{"t":1783035064,"rank":347,"points":47558,"villages":9,"ally":"54","od_total":48813,"od_att":38997,"od_def":3462,"od_sup":6354},{"t":1783120783,"rank":348,"points":49292,"villages":9,"ally":"54","od_total":48869,"od_att":38997,"od_def":3512,"od_sup":6359},{"t":1783206895,"rank":342,"points":51635,"villages":9,"ally":"54","od_total":49076,"od_att":38997,"od_def":3714,"od_sup":7765},{"t":1783294149,"rank":341,"points":53669,"villages":9,"ally":"54","od_total":64805,"od_att":53207,"od_def":3828,"od_sup":7770},{"t":1783380751,"rank":318,"points":59603,"villages":10,"ally":"54","od_total":86159,"od_att":72849,"od_def":4176,"od_sup":9134},{"t":1783466128,"rank":314,"points":61589,"villages":10,"ally":"54","od_total":88616,"od_att":75021,"od_def":4236,"od_sup":9359},{"t":1783553467,"rank":294,"points":69933,"villages":11,"ally":"54","od_total":117795,"od_att":102750,"od_def":5684,"od_sup":9361},{"t":1783640312,"rank":292,"points":72640,"villages":11,"ally":"54","od_total":120127,"od_att":102750,"od_def":5790,"od_sup":11587},{"t":1783725256,"rank":287,"points":75090,"villages":11,"ally":"54","od_total":133356,"od_att":102750,"od_def":6240,"od_sup":25584},{"t":1783798405,"rank":284,"points":76374,"villages":11,"ally":"54","od_total":169681,"od_att":103784,"od_def":9144,"od_sup":56753},{"t":1783897985,"rank":288,"points":77151,"villages":11,"ally":"54","od_total":187243,"od_att":116607,"od_def":9642,"od_sup":60820},{"t":1783984623,"rank":297,"points":68419,"villages":10,"ally":"54","od_total":188296,"od_att":116607,"od_def":24923,"od_sup":60824},{"t":1784070958,"rank":402,"points":9786,"villages":1,"ally":"0","od_total":333435,"od_att":129489,"od_def":143121,"od_sup":60825},{"t":1784157914,"rank":824,"points":26,"villages":1,"ally":"0","od_total":333451,"od_att":129489,"od_def":143137,"od_sup":60825},{"t":1784243697,"rank":810,"points":26,"villages":1,"ally":"0","od_total":333451,"od_att":129489,"od_def":143137,"od_sup":60825},{"t":1784329909,"rank":806,"points":26,"villages":1,"ally":"0","od_total":333451,"od_att":129489,"od_def":143137,"od_sup":60825},{"t":1784416465,"rank":791,"points":26,"villages":1,"ally":"0","od_total":333451,"od_att":129489,"od_def":143137,"od_sup":60825},{"t":1784502926,"rank":785,"points":26,"villages":1,"ally":"0","od_total":333451,"od_att":129489,"od_def":143137,"od_sup":60825},{"t":1784590067,"rank":775,"points":26,"villages":1,"ally":"0","od_total":333451,"od_att":129489,"od_def":143137,"od_sup":60825},{"t":1784675745,"rank":775,"points":26,"villages":1,"ally":"0","od_total":333451,"od_att":129489,"od_def":143137,"od_sup":60825},{"t":1784762840,"rank":769,"points":26,"villages":1,"ally":"0","od_total":333451,"od_att":129489,"od_def":143137,"od_sup":60825},{"t":1784803003,"rank":761,"points":26,"villages":1,"ally":"0","od_total":333451,"od_att":129489,"od_def":143137,"od_sup":60825}],"gains":[{"t":1783763109,"village":{"id":"3603","name":"022","x":465,"y":439,"points":8221},"newOwner":{"id":"2010115","name":"canmu","tribe":null},"oldOwner":{"id":"1415810","name":"Citizen","tribe":{"id":"80","tag":"SClass"}}},{"t":1783532290,"village":{"id":"3603","name":"022","x":465,"y":439,"points":8467},"newOwner":{"id":"2010115","name":"canmu","tribe":null},"oldOwner":{"id":"1415810","name":"Citizen","tribe":{"id":"80","tag":"SClass"}}},{"t":1783503765,"village":{"id":"4585","name":"071","x":466,"y":441,"points":6103},"newOwner":{"id":"2010115","name":"canmu","tribe":null},"oldOwner":{"id":"1415810","name":"Citizen","tribe":{"id":"80","tag":"SClass"}}},{"t":1783302245,"village":{"id":"2153","name":"0013","x":467,"y":441,"points":3234},"newOwner":{"id":"2010115","name":"canmu","tribe":null},"oldOwner":{"id":"2034967","name":"Perchita.","tribe":null}},{"t":1783302245,"village":{"id":"2153","name":"0013","x":467,"y":441,"points":3234},"newOwner":{"id":"2010115","name":"canmu","tribe":null},"oldOwner":{"id":"2010115","name":"canmu","tribe":null}},{"t":1783302245,"village":{"id":"2153","name":"0013","x":467,"y":441,"points":3234},"newOwner":{"id":"2010115","name":"canmu","tribe":null},"oldOwner":{"id":"2010115","name":"canmu","tribe":null}},{"t":1783020969,"village":{"id":"4988","name":"026 Raichu","x":466,"y":467,"points":6946},"newOwner":{"id":"2010115","name":"canmu","tribe":null},"oldOwner":{"id":"2001043","name":"javiervp1500","tribe":null}},{"t":1782921879,"village":{"id":"2359","name":"BACK!! 0001","x":465,"y":466,"points":9254},"newOwner":{"id":"2010115","name":"canmu","tribe":null},"oldOwner":{"id":"2001043","name":"javiervp1500","tribe":null}},{"t":1782502122,"village":{"id":"4098","name":"019- pueblo de Silver","x":461,"y":491,"points":900},"newOwner":{"id":"2010115","name":"canmu","tribe":null},"oldOwner":null},{"t":1782358127,"village":{"id":"1862","name":"006","x":467,"y":494,"points":1066},"newOwner":{"id":"2010115","name":"canmu","tribe":null},"oldOwner":null},{"t":1782204270,"village":{"id":"3875","name":"010 Oxigeno Wadasa","x":465,"y":444,"points":890},"newOwner":{"id":"2010115","name":"canmu","tribe":null},"oldOwner":null},{"t":1781784624,"village":{"id":"2150","name":"028- pueblo de mi cielo","x":465,"y":487,"points":1003},"newOwner":{"id":"2010115","name":"canmu","tribe":null},"oldOwner":null},{"t":1781553785,"village":{"id":"2582","name":"006 Knights of Cydonia","x":469,"y":490,"points":728},"newOwner":{"id":"2010115","name":"canmu","tribe":null},"oldOwner":null},{"t":1781553785,"village":{"id":"2582","name":"006 Knights of Cydonia","x":469,"y":490,"points":728},"newOwner":{"id":"2010115","name":"canmu","tribe":null},"oldOwner":{"id":"2010115","name":"canmu","tribe":null}},{"t":1781306875,"village":{"id":"236","name":"BACK","x":474,"y":490,"points":754},"newOwner":{"id":"2010115","name":"canmu","tribe":null},"oldOwner":null},{"t":1778451179,"village":{"id":"498","name":"Noble Zona M 002","x":476,"y":476,"points":4889},"newOwner":{"id":"2010115","name":"canmu","tribe":null},"oldOwner":null},{"t":1778350336,"village":{"id":"3238","name":"117-Sintm","x":444,"y":487,"points":4334},"newOwner":{"id":"2010115","name":"canmu","tribe":null},"oldOwner":{"id":"2132272","name":null,"tribe":null}},{"t":1778166806,"village":{"id":"4336","name":"013","x":482,"y":480,"points":8025},"newOwner":{"id":"2010115","name":"canmu","tribe":null},"oldOwner":{"id":"1628845","name":null,"tribe":null}}],"losses":[{"t":1784147436,"village":{"id":"2359","name":"BACK!! 0001","x":465,"y":466,"points":9786},"newOwner":{"id":"1783692","name":"sarius","tribe":{"id":"98","tag":"SINTM"}},"oldOwner":{"id":"2010115","name":"canmu","tribe":null}},{"t":1784067302,"village":{"id":"2582","name":"006 Knights of Cydonia","x":469,"y":490,"points":7234},"newOwner":{"id":"1980085","name":"Trundle","tribe":{"id":"98","tag":"SINTM"}},"oldOwner":{"id":"2010115","name":"canmu","tribe":null}},{"t":1784044401,"village":{"id":"4585","name":"071","x":466,"y":441,"points":7302},"newOwner":{"id":"1097072","name":"milrayita","tribe":{"id":"98","tag":"SINTM"}},"oldOwner":{"id":"2010115","name":"canmu","tribe":null}},{"t":1784044401,"village":{"id":"2153","name":"0013","x":467,"y":441,"points":4363},"newOwner":{"id":"1097072","name":"milrayita","tribe":{"id":"98","tag":"SINTM"}},"oldOwner":{"id":"2010115","name":"canmu","tribe":null}},{"t":1784010902,"village":{"id":"4988","name":"026 Raichu","x":466,"y":467,"points":8941},"newOwner":{"id":"1996908","name":"Reginense2","tribe":{"id":"98","tag":"SINTM"}},"oldOwner":{"id":"2010115","name":"canmu","tribe":null}},{"t":1784008994,"village":{"id":"236","name":"BACK","x":474,"y":490,"points":8258},"newOwner":{"id":"1909023","name":"F.A.L.","tribe":{"id":"98","tag":"SINTM"}},"oldOwner":{"id":"2010115","name":"canmu","tribe":null}},{"t":1784000569,"village":{"id":"4098","name":"019- pueblo de Silver","x":461,"y":491,"points":4744},"newOwner":{"id":"2179156","name":"AtIas","tribe":{"id":"80","tag":"SClass"}},"oldOwner":{"id":"2010115","name":"canmu","tribe":null}},{"t":1783990421,"village":{"id":"3875","name":"010 Oxigeno Wadasa","x":465,"y":444,"points":4720},"newOwner":{"id":"1724130","name":"hexahidratado","tribe":{"id":"54","tag":"BACK"}},"oldOwner":{"id":"2010115","name":"canmu","tribe":null}},{"t":1783989677,"village":{"id":"2150","name":"028- pueblo de mi cielo","x":465,"y":487,"points":7122},"newOwner":{"id":"904592","name":"josetxuleton05081977","tribe":{"id":"54","tag":"BACK"}},"oldOwner":{"id":"2010115","name":"canmu","tribe":null}},{"t":1783988003,"village":{"id":"1862","name":"006","x":467,"y":494,"points":5378},"newOwner":{"id":"1233834","name":"Lady La Hoya","tribe":{"id":"98","tag":"SINTM"}},"oldOwner":{"id":"2010115","name":"canmu","tribe":null}},{"t":1783977255,"village":{"id":"11704","name":"VENOM-HABRA MATANZA","x":466,"y":476,"points":8722},"newOwner":{"id":"904592","name":"josetxuleton05081977","tribe":{"id":"54","tag":"BACK"}},"oldOwner":{"id":"2010115","name":"canmu","tribe":null}},{"t":1783779686,"village":{"id":"3603","name":"022","x":465,"y":439,"points":8270},"newOwner":{"id":"2091936","name":"Manyas el Magno","tribe":{"id":"32","tag":"LaPera"}},"oldOwner":{"id":"2010115","name":"canmu","tribe":null}},{"t":1783537135,"village":{"id":"3603","name":"022","x":465,"y":439,"points":8187},"newOwner":{"id":"1415810","name":"Citizen","tribe":{"id":"80","tag":"SClass"}},"oldOwner":{"id":"2010115","name":"canmu","tribe":null}},{"t":1783302245,"village":{"id":"2153","name":"0013","x":467,"y":441,"points":3234},"newOwner":{"id":"2010115","name":"canmu","tribe":null},"oldOwner":{"id":"2010115","name":"canmu","tribe":null}},{"t":1783302245,"village":{"id":"2153","name":"0013","x":467,"y":441,"points":3234},"newOwner":{"id":"2010115","name":"canmu","tribe":null},"oldOwner":{"id":"2010115","name":"canmu","tribe":null}},{"t":1781553785,"village":{"id":"2582","name":"006 Knights of Cydonia","x":469,"y":490,"points":728},"newOwner":{"id":"2010115","name":"canmu","tribe":null},"oldOwner":{"id":"2010115","name":"canmu","tribe":null}},{"t":1779178851,"village":{"id":"3238","name":"117-Sintm","x":444,"y":487,"points":4334},"newOwner":{"id":"2174446","name":null,"tribe":null},"oldOwner":{"id":"2010115","name":"canmu","tribe":null}},{"t":1779124743,"village":{"id":"2539","name":"009 SINTM","x":475,"y":476,"points":9720},"newOwner":{"id":"1611699","name":"C1D CAMP3ADOR.","tribe":{"id":"98","tag":"SINTM"}},"oldOwner":{"id":"2010115","name":"canmu","tribe":null}},{"t":1779120367,"village":{"id":"4336","name":"013","x":482,"y":480,"points":8025},"newOwner":{"id":"2179516","name":"Shev","tribe":null},"oldOwner":{"id":"2010115","name":"canmu","tribe":null}},{"t":1779069600,"village":{"id":"498","name":"Noble Zona M 002","x":476,"y":476,"points":4889},"newOwner":{"id":"5795","name":"Manu","tribe":{"id":"54","tag":"BACK"}},"oldOwner":{"id":"2010115","name":"canmu","tribe":null}}],"villages":[{"id":"14038","name":"pueblo de canmu","x":426,"y":596,"k":54,"points":26}]}