{"profile":{"id":"87568","name":"taisapu 54","current":true,"tribe":{"id":"80","tag":"SClass"},"rank":157,"points":192928,"villages":27,"avg":7145,"od_total":1256635,"od_att":637939,"od_def":514993,"od_sup":103703,"firstSeen":1781216833,"bestRank":157,"maxPoints":192928,"maxVillages":27,"tribeChanges":1,"conquests":37,"lost":11},"series":[{"t":1781216833,"rank":200,"points":52668,"villages":10,"ally":"79","od_total":326068,"od_att":145846,"od_def":98074,"od_sup":82148},{"t":1781308451,"rank":202,"points":55135,"villages":10,"ally":"79","od_total":326734,"od_att":145846,"od_def":98740,"od_sup":82148},{"t":1781393645,"rank":238,"points":49933,"villages":9,"ally":"79","od_total":327149,"od_att":145869,"od_def":99132,"od_sup":82148},{"t":1781480337,"rank":240,"points":51886,"villages":9,"ally":"79","od_total":327463,"od_att":145869,"od_def":99446,"od_sup":82148},{"t":1781562631,"rank":250,"points":50792,"villages":8,"ally":"79","od_total":346925,"od_att":164791,"od_def":99986,"od_sup":82148},{"t":1781653778,"rank":305,"points":41885,"villages":8,"ally":"79","od_total":390857,"od_att":179982,"od_def":128727,"od_sup":82148},{"t":1781740390,"rank":359,"points":35169,"villages":8,"ally":"79","od_total":441796,"od_att":184550,"od_def":175098,"od_sup":82148},{"t":1781821584,"rank":397,"points":28536,"villages":9,"ally":"79","od_total":470240,"od_att":212608,"od_def":175484,"od_sup":82148},{"t":1781911003,"rank":407,"points":27622,"villages":10,"ally":"79","od_total":470382,"od_att":212608,"od_def":175626,"od_sup":82148},{"t":1781998647,"rank":391,"points":31849,"villages":14,"ally":"79","od_total":470490,"od_att":212703,"od_def":175639,"od_sup":82148},{"t":1782085568,"rank":376,"points":35369,"villages":14,"ally":"79","od_total":470533,"od_att":212743,"od_def":175639,"od_sup":82151},{"t":1782166633,"rank":359,"points":39391,"villages":15,"ally":"79","od_total":471122,"od_att":213311,"od_def":175657,"od_sup":82154},{"t":1782257500,"rank":351,"points":42385,"villages":15,"ally":"79","od_total":471420,"od_att":213609,"od_def":175657,"od_sup":82154},{"t":1782344129,"rank":343,"points":45431,"villages":15,"ally":"79","od_total":479647,"od_att":221832,"od_def":175657,"od_sup":82156},{"t":1782431215,"rank":320,"points":52908,"villages":17,"ally":"79","od_total":480682,"od_att":222820,"od_def":175696,"od_sup":82166},{"t":1782516956,"rank":303,"points":57643,"villages":17,"ally":"79","od_total":499720,"od_att":240367,"od_def":175696,"od_sup":83822},{"t":1782602286,"rank":292,"points":63518,"villages":17,"ally":"79","od_total":518469,"od_att":240367,"od_def":175696,"od_sup":102406},{"t":1782689481,"rank":282,"points":69026,"villages":17,"ally":"79","od_total":518525,"od_att":240507,"od_def":175696,"od_sup":102426},{"t":1782775054,"rank":264,"points":74852,"villages":18,"ally":"79","od_total":519099,"od_att":240956,"od_def":175716,"od_sup":102427},{"t":1782862685,"rank":255,"points":80580,"villages":18,"ally":"79","od_total":519141,"od_att":240974,"od_def":175729,"od_sup":102438},{"t":1782949538,"rank":249,"points":85844,"villages":18,"ally":"79","od_total":519652,"od_att":241448,"od_def":175729,"od_sup":102475},{"t":1783035064,"rank":250,"points":88845,"villages":18,"ally":"79","od_total":543780,"od_att":264701,"od_def":175729,"od_sup":103350},{"t":1783120783,"rank":233,"points":98268,"villages":19,"ally":"79","od_total":603548,"od_att":324454,"od_def":175737,"od_sup":103357},{"t":1783206895,"rank":222,"points":103371,"villages":19,"ally":"79","od_total":608325,"od_att":329217,"od_def":175745,"od_sup":103367},{"t":1783294149,"rank":212,"points":110188,"villages":20,"ally":"79","od_total":608404,"od_att":329217,"od_def":175815,"od_sup":103372},{"t":1783380751,"rank":203,"points":118409,"villages":20,"ally":"79","od_total":609305,"od_att":330100,"od_def":175815,"od_sup":103390},{"t":1783466128,"rank":194,"points":126946,"villages":22,"ally":"79","od_total":617246,"od_att":337452,"od_def":176179,"od_sup":103407},{"t":1783553467,"rank":193,"points":135396,"villages":22,"ally":"79","od_total":618708,"od_att":338895,"od_def":176387,"od_sup":103426},{"t":1783640312,"rank":189,"points":142351,"villages":23,"ally":"79","od_total":619508,"od_att":339680,"od_def":176387,"od_sup":103441},{"t":1783725256,"rank":161,"points":160777,"villages":25,"ally":"79","od_total":620509,"od_att":340029,"od_def":178512,"od_sup":103449},{"t":1783798405,"rank":160,"points":162896,"villages":25,"ally":"79","od_total":669544,"od_att":367310,"od_def":195471,"od_sup":103476},{"t":1783897985,"rank":164,"points":166350,"villages":25,"ally":"79","od_total":874496,"od_att":422891,"od_def":301837,"od_sup":103488},{"t":1783984623,"rank":159,"points":176818,"villages":26,"ally":"79","od_total":1059785,"od_att":494457,"od_def":461795,"od_sup":103551},{"t":1784070958,"rank":157,"points":181969,"villages":26,"ally":"79","od_total":1076324,"od_att":510466,"od_def":462165,"od_sup":103693},{"t":1784157914,"rank":160,"points":185556,"villages":26,"ally":"79","od_total":1151415,"od_att":567493,"od_def":480229,"od_sup":103693},{"t":1784237348,"rank":157,"points":192928,"villages":27,"ally":"80","od_total":1256635,"od_att":637939,"od_def":514993,"od_sup":103703}],"gains":[{"t":1784225508,"village":{"id":"11279","name":"N 25","x":464,"y":397,"points":2233},"newOwner":{"id":"87568","name":"taisapu 54","tribe":{"id":"80","tag":"SClass"}},"oldOwner":{"id":"1415810","name":"Citizen","tribe":{"id":"80","tag":"SClass"}}},{"t":1783985100,"village":{"id":"11294","name":"N004","x":471,"y":393,"points":767},"newOwner":{"id":"87568","name":"taisapu 54","tribe":{"id":"80","tag":"SClass"}},"oldOwner":{"id":"371560","name":"Exter Exposito","tribe":{"id":"80","tag":"SClass"}}},{"t":1783973035,"village":{"id":"12453","name":"N 24","x":472,"y":391,"points":5759},"newOwner":{"id":"87568","name":"taisapu 54","tribe":{"id":"80","tag":"SClass"}},"oldOwner":{"id":"2092837","name":"Anonymus","tribe":{"id":"32","tag":"LaPera"}}},{"t":1783697035,"village":{"id":"12426","name":"N 23","x":476,"y":387,"points":7395},"newOwner":{"id":"87568","name":"taisapu 54","tribe":{"id":"80","tag":"SClass"}},"oldOwner":{"id":"2180133","name":"Creaviudas","tribe":{"id":"45","tag":"Pera"}}},{"t":1783669925,"village":{"id":"6338","name":"Taisapu 001","x":451,"y":436,"points":8396},"newOwner":{"id":"87568","name":"taisapu 54","tribe":{"id":"80","tag":"SClass"}},"oldOwner":{"id":"87568","name":"taisapu 54","tribe":{"id":"80","tag":"SClass"}}},{"t":1783641669,"village":{"id":"6338","name":"Taisapu 001","x":451,"y":436,"points":8629},"newOwner":{"id":"87568","name":"taisapu 54","tribe":{"id":"80","tag":"SClass"}},"oldOwner":{"id":"1265225","name":"Sonny Jr.","tribe":{"id":"54","tag":"SINTM"}}},{"t":1783577975,"village":{"id":"10796","name":"N 22","x":460,"y":403,"points":751},"newOwner":{"id":"87568","name":"taisapu 54","tribe":{"id":"80","tag":"SClass"}},"oldOwner":null},{"t":1783431792,"village":{"id":"11198","name":"N 21","x":461,"y":399,"points":578},"newOwner":{"id":"87568","name":"taisapu 54","tribe":{"id":"80","tag":"SClass"}},"oldOwner":null},{"t":1783382534,"village":{"id":"9263","name":"N 20","x":459,"y":408,"points":772},"newOwner":{"id":"87568","name":"taisapu 54","tribe":{"id":"80","tag":"SClass"}},"oldOwner":null},{"t":1783273157,"village":{"id":"11132","name":"N 19","x":461,"y":400,"points":604},"newOwner":{"id":"87568","name":"taisapu 54","tribe":{"id":"80","tag":"SClass"}},"oldOwner":null},{"t":1783079967,"village":{"id":"10093","name":"N 18","x":465,"y":403,"points":5833},"newOwner":{"id":"87568","name":"taisapu 54","tribe":{"id":"80","tag":"SClass"}},"oldOwner":{"id":"2002238","name":"KIO.KAPODIPELS","tribe":null}},{"t":1782705490,"village":{"id":"13539","name":"N 17","x":450,"y":394,"points":46},"newOwner":{"id":"87568","name":"taisapu 54","tribe":{"id":"80","tag":"SClass"}},"oldOwner":null},{"t":1782381647,"village":{"id":"10276","name":"N 16","x":458,"y":403,"points":2923},"newOwner":{"id":"87568","name":"taisapu 54","tribe":{"id":"80","tag":"SClass"}},"oldOwner":{"id":"2171487","name":"idjas","tribe":{"id":"12","tag":"? _ ?"}}},{"t":1782354287,"village":{"id":"12249","name":"N 15","x":451,"y":397,"points":302},"newOwner":{"id":"87568","name":"taisapu 54","tribe":{"id":"80","tag":"SClass"}},"oldOwner":null},{"t":1782139767,"village":{"id":"12108","name":"N 14","x":472,"y":392,"points":216},"newOwner":{"id":"87568","name":"taisapu 54","tribe":{"id":"80","tag":"SClass"}},"oldOwner":null},{"t":1781970073,"village":{"id":"10244","name":"N 13","x":459,"y":402,"points":608},"newOwner":{"id":"87568","name":"taisapu 54","tribe":{"id":"80","tag":"SClass"}},"oldOwner":null},{"t":1781948969,"village":{"id":"11154","name":"N 12","x":460,"y":397,"points":438},"newOwner":{"id":"87568","name":"taisapu 54","tribe":{"id":"80","tag":"SClass"}},"oldOwner":null},{"t":1781925338,"village":{"id":"10761","name":"N 10","x":466,"y":397,"points":280},"newOwner":{"id":"87568","name":"taisapu 54","tribe":{"id":"80","tag":"SClass"}},"oldOwner":null},{"t":1781916006,"village":{"id":"10620","name":"N 11","x":458,"y":401,"points":360},"newOwner":{"id":"87568","name":"taisapu 54","tribe":{"id":"80","tag":"SClass"}},"oldOwner":null},{"t":1781842137,"village":{"id":"12042","name":"N 09","x":467,"y":393,"points":189},"newOwner":{"id":"87568","name":"taisapu 54","tribe":{"id":"80","tag":"SClass"}},"oldOwner":null},{"t":1781831868,"village":{"id":"11712","name":"N 08","x":455,"y":399,"points":278},"newOwner":{"id":"87568","name":"taisapu 54","tribe":{"id":"80","tag":"SClass"}},"oldOwner":{"id":"2180835","name":null,"tribe":null}},{"t":1781796225,"village":{"id":"10905","name":"N 07","x":467,"y":396,"points":336},"newOwner":{"id":"87568","name":"taisapu 54","tribe":{"id":"80","tag":"SClass"}},"oldOwner":null},{"t":1781773084,"village":{"id":"10174","name":"N 06","x":459,"y":407,"points":969},"newOwner":{"id":"87568","name":"taisapu 54","tribe":{"id":"80","tag":"SClass"}},"oldOwner":null},{"t":1781695031,"village":{"id":"11937","name":"N 05","x":462,"y":393,"points":218},"newOwner":{"id":"87568","name":"taisapu 54","tribe":{"id":"80","tag":"SClass"}},"oldOwner":null},{"t":1781654907,"village":{"id":"9960","name":"N 04","x":458,"y":406,"points":2662},"newOwner":{"id":"87568","name":"taisapu 54","tribe":{"id":"80","tag":"SClass"}},"oldOwner":{"id":"1985825","name":null,"tribe":null}},{"t":1781631856,"village":{"id":"11169","name":"N 02","x":462,"y":398,"points":254},"newOwner":{"id":"87568","name":"taisapu 54","tribe":{"id":"80","tag":"SClass"}},"oldOwner":null},{"t":1781609374,"village":{"id":"11370","name":"N 03","x":459,"y":400,"points":276},"newOwner":{"id":"87568","name":"taisapu 54","tribe":{"id":"80","tag":"SClass"}},"oldOwner":null},{"t":1781567595,"village":{"id":"10732","name":"N 01","x":460,"y":400,"points":7771},"newOwner":{"id":"87568","name":"taisapu 54","tribe":{"id":"80","tag":"SClass"}},"oldOwner":{"id":"1985825","name":null,"tribe":null}},{"t":1780957649,"village":{"id":"9960","name":"N 04","x":458,"y":406,"points":1295},"newOwner":{"id":"87568","name":"taisapu 54","tribe":{"id":"80","tag":"SClass"}},"oldOwner":null},{"t":1780784476,"village":{"id":"143","name":"014 Noble","x":454,"y":446,"points":2135},"newOwner":{"id":"87568","name":"taisapu 54","tribe":{"id":"80","tag":"SClass"}},"oldOwner":null},{"t":1780694167,"village":{"id":"1892","name":"Maik20","x":452,"y":446,"points":2660},"newOwner":{"id":"87568","name":"taisapu 54","tribe":{"id":"80","tag":"SClass"}},"oldOwner":null},{"t":1780111571,"village":{"id":"5042","name":"009 enanito chileno","x":453,"y":446,"points":4226},"newOwner":{"id":"87568","name":"taisapu 54","tribe":{"id":"80","tag":"SClass"}},"oldOwner":null},{"t":1779898782,"village":{"id":"6219","name":"Maik17","x":447,"y":442,"points":3977},"newOwner":{"id":"87568","name":"taisapu 54","tribe":{"id":"80","tag":"SClass"}},"oldOwner":null},{"t":1779031985,"village":{"id":"6648","name":"Maik15","x":440,"y":445,"points":7086},"newOwner":{"id":"87568","name":"taisapu 54","tribe":{"id":"80","tag":"SClass"}},"oldOwner":null},{"t":1778547018,"village":{"id":"6939","name":"Maik19","x":444,"y":437,"points":8491},"newOwner":{"id":"87568","name":"taisapu 54","tribe":{"id":"80","tag":"SClass"}},"oldOwner":null},{"t":1778452545,"village":{"id":"6234","name":"Maik16","x":450,"y":441,"points":7370},"newOwner":{"id":"87568","name":"taisapu 54","tribe":{"id":"80","tag":"SClass"}},"oldOwner":null},{"t":1777959823,"village":{"id":"6774","name":"Taisapu 002","x":446,"y":438,"points":7705},"newOwner":{"id":"87568","name":"taisapu 54","tribe":{"id":"80","tag":"SClass"}},"oldOwner":null}],"losses":[{"t":1784042928,"village":{"id":"11294","name":"N004","x":471,"y":393,"points":804},"newOwner":{"id":"371560","name":"Exter Exposito","tribe":{"id":"80","tag":"SClass"}},"oldOwner":{"id":"87568","name":"taisapu 54","tribe":{"id":"80","tag":"SClass"}}},{"t":1783669925,"village":{"id":"6338","name":"Taisapu 001","x":451,"y":436,"points":8396},"newOwner":{"id":"87568","name":"taisapu 54","tribe":{"id":"80","tag":"SClass"}},"oldOwner":{"id":"87568","name":"taisapu 54","tribe":{"id":"80","tag":"SClass"}}},{"t":1781829259,"village":{"id":"1892","name":"Maik20","x":452,"y":446,"points":3769},"newOwner":{"id":"2084332","name":"Maik","tribe":{"id":"79","tag":"Class"}},"oldOwner":{"id":"87568","name":"taisapu 54","tribe":{"id":"80","tag":"SClass"}}},{"t":1781766420,"village":{"id":"6939","name":"Maik19","x":444,"y":437,"points":9188},"newOwner":{"id":"2084332","name":"Maik","tribe":{"id":"79","tag":"Class"}},"oldOwner":{"id":"87568","name":"taisapu 54","tribe":{"id":"80","tag":"SClass"}}},{"t":1781732923,"village":{"id":"6244","name":"Maik18","x":447,"y":441,"points":8135},"newOwner":{"id":"2084332","name":"Maik","tribe":{"id":"79","tag":"Class"}},"oldOwner":{"id":"87568","name":"taisapu 54","tribe":{"id":"80","tag":"SClass"}}},{"t":1781707579,"village":{"id":"143","name":"014 Noble","x":454,"y":446,"points":3405},"newOwner":{"id":"156480","name":"tetitet","tribe":{"id":"79","tag":"Class"}},"oldOwner":{"id":"87568","name":"taisapu 54","tribe":{"id":"80","tag":"SClass"}}},{"t":1781646631,"village":{"id":"6219","name":"Maik17","x":447,"y":442,"points":5098},"newOwner":{"id":"2084332","name":"Maik","tribe":{"id":"79","tag":"Class"}},"oldOwner":{"id":"87568","name":"taisapu 54","tribe":{"id":"80","tag":"SClass"}}},{"t":1781579461,"village":{"id":"5042","name":"009 enanito chileno","x":453,"y":446,"points":4224},"newOwner":{"id":"1099107","name":"R2D2","tribe":{"id":"98","tag":"BACK"}},"oldOwner":{"id":"87568","name":"taisapu 54","tribe":{"id":"80","tag":"SClass"}}},{"t":1781577276,"village":{"id":"6234","name":"Maik16","x":450,"y":441,"points":8568},"newOwner":{"id":"2084332","name":"Maik","tribe":{"id":"79","tag":"Class"}},"oldOwner":{"id":"87568","name":"taisapu 54","tribe":{"id":"80","tag":"SClass"}}},{"t":1781505111,"village":{"id":"9960","name":"N 04","x":458,"y":406,"points":2655},"newOwner":{"id":"1985825","name":null,"tribe":null},"oldOwner":{"id":"87568","name":"taisapu 54","tribe":{"id":"80","tag":"SClass"}}},{"t":1781331986,"village":{"id":"6648","name":"Maik15","x":440,"y":445,"points":7429},"newOwner":{"id":"2084332","name":"Maik","tribe":{"id":"79","tag":"Class"}},"oldOwner":{"id":"87568","name":"taisapu 54","tribe":{"id":"80","tag":"SClass"}}}],"villages":[{"id":"10732","name":"N 01","x":460,"y":400,"k":44,"points":9347},{"id":"11169","name":"N 02","x":462,"y":398,"k":34,"points":9954},{"id":"11370","name":"N 03","x":459,"y":400,"k":44,"points":6629},{"id":"9960","name":"N 04","x":458,"y":406,"k":44,"points":9549},{"id":"11937","name":"N 05","x":462,"y":393,"k":34,"points":9268},{"id":"10174","name":"N 06","x":459,"y":407,"k":44,"points":7434},{"id":"10905","name":"N 07","x":467,"y":396,"k":34,"points":8240},{"id":"11712","name":"N 08","x":455,"y":399,"k":34,"points":8037},{"id":"12042","name":"N 09","x":467,"y":393,"k":34,"points":8096},{"id":"10761","name":"N 10","x":466,"y":397,"k":34,"points":7986},{"id":"10620","name":"N 11","x":458,"y":401,"k":44,"points":7249},{"id":"11154","name":"N 12","x":460,"y":397,"k":34,"points":6863},{"id":"10244","name":"N 13","x":459,"y":402,"k":44,"points":8337},{"id":"12108","name":"N 14","x":472,"y":392,"k":34,"points":7868},{"id":"12249","name":"N 15","x":451,"y":397,"k":34,"points":7238},{"id":"10276","name":"N 16","x":458,"y":403,"k":44,"points":7846},{"id":"13539","name":"N 17","x":450,"y":394,"k":34,"points":5502},{"id":"10093","name":"N 18","x":465,"y":403,"k":44,"points":8509},{"id":"11132","name":"N 19","x":461,"y":400,"k":44,"points":4405},{"id":"9263","name":"N 20","x":459,"y":408,"k":44,"points":3753},{"id":"11198","name":"N 21","x":461,"y":399,"k":34,"points":3252},{"id":"10796","name":"N 22","x":460,"y":403,"k":44,"points":1812},{"id":"12426","name":"N 23","x":476,"y":387,"k":34,"points":8096},{"id":"12453","name":"N 24","x":472,"y":391,"k":34,"points":5938},{"id":"11279","name":"N 25","x":464,"y":397,"k":34,"points":2173},{"id":"6338","name":"Taisapu 001","x":451,"y":436,"k":44,"points":9572},{"id":"6774","name":"Taisapu 002","x":446,"y":438,"k":44,"points":9975}]}